instawebhooks/__init__.py
instawebhooks/__main__.py
instawebhooks/parser.py
instawebhooks-0.1.4.dist-info/licenses/LICENSE.txt
instawebhooks-0.1.4.dist-info/METADATA
instawebhooks-0.1.4.dist-info/WHEEL
instawebhooks-0.1.4.dist-info/entry_points.txt
instawebhooks-0.1.4.dist-info/top_level.txt
instawebhooks-0.1.4.dist-info/RECORD
