Metadata-Version: 2.4
Name: instawebhooks
Version: 0.1.4
Summary: Discord webhooks for new Instagram posts from any profile
Author-email: Ryan Luu <ryan.luu@ryanluu.dev>
Project-URL: Homepage, https://github.com/RyanLua/InstaWebhooks
Project-URL: Documentation, https://github.com/RyanLua/InstaWebhooks/wiki
Project-URL: Repository, https://github.com/RyanLua/InstaWebhooks.git
Project-URL: Issues, https://github.com/RyanLua/InstaWebhooks/issues
Project-URL: Sponsor, https://github.com/sponsors/RyanLua
Keywords: webhooks,feed,embed,Instagram,Discord,CLI
Classifier: Development Status :: 4 - Beta
Classifier: Environment :: Console
Classifier: Intended Audience :: End Users/Desktop
Classifier: Topic :: Utilities
Classifier: Topic :: Internet
Classifier: Topic :: Communications
Classifier: License :: OSI Approved :: MIT License
Classifier: Programming Language :: Python :: 3
Classifier: Programming Language :: Python :: 3.8
Classifier: Programming Language :: Python :: 3.9
Classifier: Programming Language :: Python :: 3.10
Classifier: Programming Language :: Python :: 3.11
Classifier: Programming Language :: Python :: 3.12
Classifier: Programming Language :: Python :: 3.13
Classifier: Programming Language :: Python :: 3 :: Only
Requires-Python: >=3.8
License-File: LICENSE.txt
Requires-Dist: aiohttp
Requires-Dist: discord.py
Requires-Dist: requests
Requires-Dist: instaloader
Dynamic: license-file
